{"1010": {"questions": [2, 4, 1, 3], "music_order": ["relax", "energy", "nothing", "nothing"]}, "1211": {"questions": [2, 3, 4, 1], "music_order": ["nothing", "relax", "energy", "nothing"]}, "1412": {"questions": [2, 1, 4, 3], "music_order": ["nothing", "energy", "relax", "nothing"]}, "1613": {"questions": [1, 2, 3, 4], "music_order": ["nothing", "energy", "relax", "nothing"]}, "1814": {"questions": [1, 3, 2, 4], "music_order": ["relax", "nothing", "energy", "nothing"]}, "1a15": {"questions": [2, 3, 1, 4], "music_order": ["relax", "nothing", "energy", "nothing"]}, "1c16": {"questions": [2, 3, 4, 1], "music_order": ["energy", "relax", "nothing", "nothing"]}, "1e17": {"questions": [1, 4, 2, 3], "music_order": ["relax", "energy", "nothing", "nothing"]}, "2018": {"questions": [1, 4, 3, 2], "music_order": ["relax", "energy", "nothing", "nothing"]}, "2219": {"questions": [2, 4, 1, 3], "music_order": ["energy", "nothing", "relax", "nothing"]}}